bosha/__init__.py
bosha/client/__init__.py
bosha/client/web_client/app.py
bosha/client/web_client/templates/index.html
bosha/client/web_client/utils/ws_client.py
bosha/models/__init__.py
bosha/models/cli.py
bosha/models/model_manager.py
bosha/server/__init__.py
bosha/server/config.py
bosha/server/main.py
bosha/server/models/__init__.py
bosha/server/models/end_to_end_sign_recognition.py
bosha/server/models/gesture_password.py
bosha/server/models/hand_pose_estimator.py
bosha/server/models/hand_sign_model.py
bosha/server/models/openvino_model.py
bosha/server/models/preprocessing.py
bosha/server/models/semantic_validator.py
bosha/server/models/sentence_generator.py
bosha/server/models/transformer_sign_recognizer.py
bosha/server/models/yolov8_hand_detector.py
bosha/server/services/__init__.py
bosha/server/services/agora_service.py
bosha/server/services/resource_manager.py
bosha/server/services/video_processor.py
bosha/server/services/websocket_service.py
bosha/server/utils/__init__.py
bosha/server/utils/crypto.py
bosha/server/utils/logger.py
bosha/training/__init__.py
bosha/training/config.json
bosha/training/convert_to_openvino.py
bosha/training/evaluate.py
bosha/training/train.py
bos_ha-1.1.2.dist-info/METADATA
bos_ha-1.1.2.dist-info/WHEEL
bos_ha-1.1.2.dist-info/entry_points.txt
bos_ha-1.1.2.dist-info/top_level.txt
bos_ha-1.1.2.dist-info/RECORD
