Metadata-Version: 2.4
Name: BOS-HA
Version: 1.1.2
Summary: 基于深度学习的手语识别系统
Home-page: https://github.com/bos-ha/BOS-HA
Author: BOS-HA Team
Author-email: contact@bos-ha.com
License: MIT
Keywords: sign-language-recognition,deep-learning,computer-vision,openvino
Classifier: Development Status :: 5 - Production/Stable
Classifier: Intended Audience :: Developers
Classifier: Intended Audience :: Science/Research
Classifier: Intended Audience :: Education
Classifier: Topic :: Scientific/Engineering :: Artificial Intelligence
Classifier: Topic :: Multimedia :: Sound/Audio :: Speech
Classifier: Topic :: Software Development :: Libraries :: Python Modules
Classifier: License :: OSI Approved :: MIT License
Classifier: Programming Language :: Python :: 3
Classifier: Programming Language :: Python :: 3.7
Classifier: Programming Language :: Python :: 3.8
Classifier: Programming Language :: Python :: 3.9
Classifier: Programming Language :: Python :: 3.10
Classifier: Programming Language :: Python :: 3.11
Classifier: Operating System :: OS Independent
Requires-Python: >=3.7
Requires-Dist: torch>=2.0.0
Requires-Dist: torchvision>=0.15.0
Requires-Dist: transformers>=4.30.0
Requires-Dist: fastapi>=0.100.0
Requires-Dist: uvicorn>=0.22.0
Requires-Dist: websockets>=11.0.0
Requires-Dist: flask>=2.3.0
Requires-Dist: flask-socketio>=5.3.0
Requires-Dist: flask-babel>=4.0.0
Requires-Dist: babel>=2.12.0
Requires-Dist: opencv-python>=4.8.0
Requires-Dist: numpy>=1.24.0
Requires-Dist: tqdm>=4.65.0
Requires-Dist: pillow>=10.0.0
Requires-Dist: requests>=2.31.0
Requires-Dist: openvino>=2024.0.0
Requires-Dist: openvino-dev>=2024.0.0
Requires-Dist: onnx>=1.14.0
Requires-Dist: onnxscript>=0.5.0
Provides-Extra: dev
Requires-Dist: pytest>=7.4.0; extra == "dev"
Requires-Dist: black>=23.3.0; extra == "dev"
Requires-Dist: flake8>=6.0.0; extra == "dev"
Requires-Dist: mypy>=1.3.0; extra == "dev"
Requires-Dist: pytest-cov>=4.1.0; extra == "dev"
Dynamic: author
Dynamic: author-email
Dynamic: classifier
Dynamic: description
Dynamic: description-content-type
Dynamic: home-page
Dynamic: keywords
Dynamic: license
Dynamic: provides-extra
Dynamic: requires-dist
Dynamic: requires-python
Dynamic: summary
